Topsis/Topsis_401903010.py
Topsis/__init__.py
topsis_Dhairya_401903010-1.0.1.dist-info/METADATA
topsis_Dhairya_401903010-1.0.1.dist-info/WHEEL
topsis_Dhairya_401903010-1.0.1.dist-info/top_level.txt
topsis_Dhairya_401903010-1.0.1.dist-info/RECORD
